plogging/__init__.py
plogging/_converter.py
plogging/_formatter.py
plogging/_level_container.py
plogging/_palette.py
plogging/constants.py
plogging/types.py
plogging/utils.py
plogging-0.0.1.dist-info/LICENSE
plogging-0.0.1.dist-info/METADATA
plogging-0.0.1.dist-info/WHEEL
plogging-0.0.1.dist-info/top_level.txt
plogging-0.0.1.dist-info/RECORD
