Metadata-Version: 2.1
Name: plogging
Version: 0.0.1
Summary: A formatter and set of utilities that bring pretty, highly-customizable and colored log messages to the standard logging library
Author-email: "Tanner B. Corcoran" <tannerbcorcoran@gmail.com>
Project-URL: Homepage, https://github.com/tanrbobanr/plogging
Classifier: Programming Language :: Python :: 3
Classifier: License :: OSI Approved :: MIT License
Classifier: Operating System :: OS Independent
Requires-Python: >=3.9
License-File: LICENSE
